oast/analyze.py
oast/transform_image.py
oast/transformations.py
oast-0.0.3.dist-info/LICENSE
oast-0.0.3.dist-info/METADATA
oast-0.0.3.dist-info/WHEEL
oast-0.0.3.dist-info/entry_points.txt
oast-0.0.3.dist-info/top_level.txt
oast-0.0.3.dist-info/RECORD
