Metadata-Version: 2.1
Name: oast
Version: 0.0.3
Summary: our awesome spectral toolbox
Home-page: https://github.com/jag426/oast
Author: Aaron Gustafson
Author-email: jag426@cornell.edu
Classifier: Programming Language :: Python :: 3
Classifier: License :: OSI Approved :: The Unlicense (Unlicense)
Classifier: Operating System :: OS Independent
Requires-Python: >=3.8
License-File: LICENSE
Requires-Dist: joblib
Requires-Dist: matplotlib
Requires-Dist: numpy
Requires-Dist: pandas
Requires-Dist: spectral
